Workbook

Sheet 0. README
A1: ZIMLIVESTOCK
A2: Financial Model — 5-year scaling B2B-SaaS platform (v3.0)
A3: v3.0 · Tatenda Nyemudzo · June 2026 · scaling platform (self-funded, working-capital buffer)
A6: WHAT'S IN THIS WORKBOOK
A8: 1. Assumptions — All inputs in gold cells. Pricing (4 lines), adoption, scale ramp, costs.
A9: 2. House ramp — Houses live by year (5 → 8 → 12 → 16 → 20), tier mix, GMV onto rails.
A10: 3. Revenue — Year-by-year across the 4 revenue lines, totaled, + revenue mix.
A11: 4. Costs — Year-by-year across the 4 cost lines (founder salary inside payroll).
A12: 5. P&L summary — Year-by-year revenue, costs, surplus, cumulative, GMV, drivers + notes.
A15: THE FRAME — A SCALING B2B-SaaS PLATFORM
A17: · Auction houses ONBOARD as isolated (RLS) tenants via a self-serve wizard and pay a one-off
A18: onboarding fee + a monthly platform subscription + a thin 0.75% take on settled GMV.
... A49: · Zim-specific: USD scarcity / collection friction, currency volatility. All figures USD.

Sheet 1. Assumptions
A1: ZIMLIVESTOCK — FINANCIAL MODEL ASSUMPTIONS (v3.0, scaling B2B-SaaS platform)
A2: Gold cells = inputs (edit these). White cells = calculations. Scaling case: ~20 houses over 5 years, field-honest adoption, small team, self-funded with a working-capital buffer.
A4: PRICING — onboarding fee (one-off, per house)
A5: Onboarding fee — Tier A (anchor house) | B5: 3500 | C5: Self-serve wizard onboarding; ~6-min RLS-isolated tenant
A6: Onboarding fee — Tier B (mid-market) | B6: 2500
A7: Onboarding fee — Tier C (smaller house) | B7: 1500
A8: Onboarding fee — Pilot | B8: 1000 | C8: Credited toward the full tier fee on conversion (never paid twice)
A10: PRICING — monthly platform subscription (per house)
A11: Subscription — Tier A | B11: 1500 | C11: Recurring platform subscription
A12: Subscription — Tier B | B12: 1200
A13: Subscription — Tier C | B13: 900
A14: Subscription — Pilot | B14: 1000 | C14: US$1,000/mo for 90 days, then converts to signed tier
A16: PRICING — transaction take + transport
A17: Transaction take % | B17: 0.0075 | C17: 0.75% of settled GMV, on TOP of Paynow's fee
A18: Transport — base booking leg | B18: 15 | C18: Buyer-facing flat fee; platform keeps only this leg
A19: Transport — per km (transporter keeps) | B19: 0.35 | C19: Distance haul priced + kept by the transporter
A20: Transport — quote cap | B20: 250 | C20: Caps the buyer quote
A21: Transport — platform NET per booking | B21: 12 | C21: US$15 booking leg less ~US$3 processing
A23: ADOPTION & DRIVERS — held field-honest (NOT a growth lever)
A24: Blended digital adoption — Year 1 | B24: 0.105 | C24: Below the ~15% mature ceiling for a manual cash market
A25: Blended digital adoption — Year 5 | B25: 0.137 | C25: Still field-honest at Y5
A26: Avg digital ticket | B26: 650 | C26: Per settled digital transaction
A27: Transport attach-rate — Year 1 | B27: 0.05 | C27: Ramps 5% -> 24% over Y1..Y5
A28: Transport attach-rate — Year 5 | B28: 0.24 | C28: Consumer line diversifies revenue over time
A30: SCALE & RAMP — houses live at year-end
A31: Houses live — Year 1 | B31: 5 | C31: Anchors-first; ~1/3 of the ~40-60 house market by Y5
A32: Houses live — Year 2 | B32: 8
A33: Houses live — Year 3 | B33: 12
A34: Houses live — Year 4 | B34: 16
A35: Houses live — Year 5 | B35: 20 | C35: Subscription uses a half-year go-live convention
A37: COSTS — small team, self-funded with a working-capital buffer
A38: Payroll — Year 1 | B38: 36000 | C38: Founder salary sits inside payroll
A39: Payroll — Year 5 | B39: 198000 | C39: Funds a real ~9-13 person org (not a lean 4-person team)
A40: Infrastructure — Year 1 | B40: 3600 | C40: Supabase + Vercel + Cloudflare + channels
A41: Other (BD / travel / mktg) — Year 1 | B41: 9000 | C41: Business development, travel, marketing

Sheet 2. House ramp
A1: HOUSE RAMP — ~20 houses over five years (5 → 8 → 12 → 16 → 20 live, anchors-first)
B3: Year 1 | C3: Year 2 | D3: Year 3 | E3: Year 4 | F3: Year 5
A4: Houses live (EOY) | B4: 5 | C4: 8 | D4: 12 | E4: 16 | F4: 20
A5: Tier A onboarded (year) | B5: 3 | C5: 1 | D5: 1 | E5: 1 | F5: 1
A6: Tier B onboarded (year) | B6: 1 | C6: 1 | D6: 2 | E6: 2 | F6: 2
A7: Tier C onboarded (year) | B7: 1 | C7: 1 | D7: 1 | E7: 1 | F7: 1
A8: Cumulative Tier A | B8: 3 | C8: 4 | D8: 5 | E8: 6 | F8: 7
A9: Cumulative Tier B | B9: 1 | C9: 2 | D9: 4 | E9: 6 | F9: 8
A10: Cumulative Tier C | B10: 1 | C10: 2 | D10: 3 | E10: 4 | F10: 5
A12: Blended digital adoption | B12: 0.105 | C12: 0.115 | D12: 0.123 | E12: 0.13 | F12: 0.137
A13: Digital transactions | B13: 1376 | C13: 3790 | D13: 5667 | E13: 8170 | F13: 10999
A14: Transport attach-rate | B14: 0.05 | C14: 0.09 | D14: 0.14 | E14: 0.19 | F14: 0.24
A16: GMV onto Paynow rails | B16: 894600 | C16: 2463200 | D16: 3683300 | E16: 5310800 | F16: 7149100
A18: Cumulative tier mix runs 3A/1B/1C (Y1) → 7A/8B/5C (Y5). Subscription uses a half-year go-live convention: the current-year cohort is billed 6 months, prior cohorts 12. Avg digital ticket US$650. Adoption stays field-honest (below the ~15% mature ceiling) — it is NOT used as a growth lever; growth rides house count + transport.

Sheet 3. Revenue
A1: ANNUAL REVENUE — 5-year projection across four lines
A3: Revenue line | B3: Year 1 | C3: Year 2 | D3: Year 3 | E3: Year 4 | F3: Year 5 | G3: 5-yr total
A4: Onboarding (one-off) | B4: 14500 | C4: 7500 | D4: 10000 | E4: 10000 | F4: 10000 | G4: =SUM(B4:F4)
A5: Platform subscription | B5: 39600 | C5: 100800 | D5: 151200 | E5: 208800 | F5: 266400 | G5: =SUM(B5:F5)
A6: Transaction take (0.75%) | B6: 6710 | C6: 18474 | D6: 27625 | E6: 39831 | F6: 53618 | G6: =SUM(B6:F6)
A7: Transport (consumer line) | B7: 826 | C7: 4093 | D7: 9521 | E7: 18628 | F7: 31677 | G7: =SUM(B7:F7)
A8: REVENUE TOTAL | B8: =SUM(B4:B7) | C8: =SUM(C4:C7) | D8: =SUM(D4:D7) | E8: =SUM(E4:E7) | F8: =SUM(F4:F7) | G8: =SUM(B8:F8)
A10: REVENUE MIX
A11: Auction-house revenue % | B11: 0.987 | C11: 0.969 | D11: 0.952 | E11: 0.933 | F11: 0.912
A12: Consumer-transport revenue % | B12: 0.013 | C12: 0.031 | D12: 0.048 | E12: 0.067 | F12: 0.088
A13: 5-yr revenue total: US$1,029,803 · onboarding US$52,000 · subscription US$766,800 · take US$146,258 · transport US$64,745

Sheet 4. Costs
A1: ANNUAL COSTS — small team + infrastructure (founder salary inside payroll)
A3: Cost line | B3: Year 1 | C3: Year 2 | D3: Year 3 | E3: Year 4 | F3: Year 5 | G3: 5-yr total
A4: Infrastructure | B4: 3600 | C4: 3960 | D4: 4440 | E4: 4920 | F4: 5400 | G4: =SUM(B4:F4)
A5: Payroll (incl. founder) | B5: 36000 | C5: 66000 | D5: 108000 | E5: 150000 | F5: 198000 | G5: =SUM(B5:F5)
A6: Pass-through (Paynow) | B6: 241 | C6: 314 | D6: 370 | E6: 445 | F6: 530 | G6: =SUM(B6:F6)
A7: Other (BD / travel / mktg) | B7: 9000 | C7: 14000 | D7: 20000 | E7: 26000 | F7: 32000 | G7: =SUM(B7:F7)
A8: COSTS TOTAL | B8: =SUM(B4:B7) | C8: =SUM(C4:C7) | D8: =SUM(D4:D7) | E8: =SUM(E4:E7) | F8: =SUM(F4:F7) | G8: =SUM(B8:F8)
A10: 5-yr costs total: US$683,220 · Y5 payroll US$198,000 funds a real ~9-13 person org (NOT a lean 4-person team).

Sheet 5. P&L summary
A1: P&L SUMMARY — year by year (v3.0 scaling platform)
B3: Year 1 | C3: Year 2 | D3: Year 3 | E3: Year 4 | F3: Year 5 | G3: 5-yr total
A4: Revenue | B4: ='3. Revenue'!B8 | C4: ='3. Revenue'!C8 | D4: ='3. Revenue'!D8 | E4: ='3. Revenue'!E8 | F4: ='3. Revenue'!F8 | G4: =SUM(B4:F4)
A5: Costs | B5: =-'4. Costs'!B8 | C5: =-'4. Costs'!C8 | D5: =-'4. Costs'!D8 | E5: =-'4. Costs'!E8 | F5: =-'4. Costs'!F8 | G5: =SUM(B5:F5)
A6: SURPLUS | B6: =B4+B5 | C6: =C4+C5 | D6: =D4+D5 | E6: =E4+E5 | F6: =F4+F5 | G6: =SUM(B6:F6)
A7: Cumulative surplus | B7: =B6 | C7: =C6+B7 | D7: =D6+C7 | E7: =E6+D7 | F7: =F6+E7
A8: GMV onto Paynow rails | B8: 894600 | C8: 2463200 | D8: 3683300 | E8: 5310800 | F8: 7149100 | G8: =SUM(B8:F8)
A10: DRIVERS
B11: Year 1 | C11: Year 2 | D11: Year 3 | E11: Year 4 | F11: Year 5
A12: Houses live (EOY) | B12: 5 | C12: 8 | D12: 12 | E12: 16 | F12: 20
A13: Blended adoption | B13: 0.105 | C13: 0.115 | D13: 0.123 | E13: 0.13 | F13: 0.137
A14: Digital transactions | B14: 1376 | C14: 3790 | D14: 5667 | E14: 8170 | F14: 10999
A15: Transport attach-rate | B15: 0.05 | C15: 0.09 | D15: 0.14 | E15: 0.19 | F15: 0.24
A16: Auction-house revenue % | B16: 0.987 | C16: 0.969 | D16: 0.952 | E16: 0.933 | F16: 0.912
A17: Consumer-transport revenue % | B17: 0.013 | C17: 0.031 | D17: 0.048 | E17: 0.067 | F17: 0.088
A19: NOTES — read before quoting any number
A20: • SCALING B2B-SaaS PLATFORM. ~20 houses over 5 years (5 → 8 → 12 → 16 → 20 live, anchors-first), about 1/3 of the ~40-60 house market. A self-serve onboarding wizard (/operators → admin approval → ~6-min RLS-isolated tenant, no SQL) makes scale low-touch.
A21: • Five live channels: web/PWA, WhatsApp, USSD, BillPay-as-biller, Facebook Messenger. B2B today (auction houses), B2B2C tomorrow (consumer transport diversifies revenue: 1.3% of revenue in Y1 → 8.8% in Y5).
A22: • Positive surplus every year: +US$12,795 (Y1) → +US$125,765 (Y5); +US$346,583 cumulative over 5 years. No equity-requiring trough. The Y1 cushion is thin (~3.5 weeks of opex), so hold a 2-3 month opex working-capital buffer.
A23: • Small team, largely SELF-FUNDED (NOT external equity). Y5 payroll US$198,000 funds a real ~9-13 person org — NOT a 'lean 4-person team'. The founder draws a salary that sits inside payroll.
A24: • Subscription-led: Y5 subscription US$266,400 of US$361,695 total. Recurring spine is reliable; the 0.75% transaction take compounds with GMV; transport is the consumer diversification line.
A25: • GMV routed onto Paynow rails: US$894,600 (Y1) → US$7,149,100 (Y5); ~US$19.5M over 5 years. Paynow is the settlement spine (Integration ID 23997; Stripe diaspora fallback). 3 of 4 national livestock-digitization initiatives have NO settlement layer — we are it.
A26: • Field-honest caveats: digital adoption stays ~10.5-13.7% (below the ~15% mature ceiling) and is NOT used as a growth lever — growth rides house count + transport. The single MOST AGGRESSIVE assumption is landing 3 of ~8 Tier A anchors in Year 1. All figures USD.
